{
  "suffix_name": "ຜູ້ຈັດສົ່ງ",
  "sign_in": "ເຂົ້າລະບົບ",
  "email": "ອີເມວ",
  "password": "ລະຫັດ",
  "confirm_password": "ຢືນຢັນລະຫັດ",
  "remember_me": "ຈື່ຂ້ອຍໄວ້",
  "forgot_password": "ລືມລະຫັດ",
  "phone": "ໂທລະສັບ",
  "enter_email_address": "ລະບຸອີເມວ",
  "enter_a_valid_email_address": "ໃສ່ອີເມວທີ່ຖືກຕ້ອງ",
  "enter_phone_number": "ໃ່ເບີໂທຂອງທ່ານ",
  "invalid_phone_number": "ເບີໂທບໍ່ຖືກຕ້ອງ. ກະລຸນາໃສ່ເບີໂທຂອງທ່ານໂດຍບໍ່ຕ້ອງໃສ່ລະຫັດປະເທດ",
  "enter_password": "ໃສ່ລະຫັດຜ່ານ",
  "password_does_not_matched": "ຢືນຢັນລະຫັດຜ່ານບໍ່ກົງກັນ",
  "password_should_be": "ລະຫັດຜ່ານຕ້ອງມີຢ່າງໜ້ອຍ 6 ຕົວອັກສອນ",
  "otp_verification": "ການຢືນຢັນຜ່ານ OTP",
  "enter_the_verification_sent_to": "ໃສ່ລະຫັດຢືນຢັນ (OTP) ທີ່ສົ່ງຫາ",
  "verify": "ຢືນຢັນ",
  "did_not_receive_the_code": "ບໍ່ໄດ້ຮັບລະຫັດ?",
  "resent": "ສົ່ງໃໝ່",
  "verified": "ຢືນຢັນແລ້ວ",
  "resend_code_successful": "ສົ່ງລະຫັດໃໝ່ສຳເລັດ",
  "please_enter_mobile": "ກະລຸນາໃສ່ເບີທີ່ທ່ານໃຊ້ລົງທະບຽນ ພວກເຮົາຈື່ງຈະສາມາດຊ່ວຍທ່ານໃນການກູ້ຄືນລະຫັດໄດ້.",
  "done": "ສຳເລັດ",
  "enter_new_password": "ໃສ່ລະຫັດຜ່ານໃໝ່ ແລະ ຢືນຢັນ.",
  "new_password": "ລະຫັດໃໝ່",
  "reset_password": "ຕັ້ງລະຫັດໃໝ່",
  "online": "ອອນລາຍ",
  "offline": "ອັອຟລາຍ",
  "active_order": "ອໍເດີ້ປັດຈຸບັນ",
  "order_id": "ເລກທີອໍເດີ",
  "orders": "ອໍເດີ້",
  "view_all": "ເບິ່ງໝົດ",
  "details": "ລາຍລະອຽດ",
  "delivery": "ການສົ່ງ",
  "todays_orders": "ອໍເດີ້ມື້ນີ້",
  "this_week_orders": "ອໍເດີ້ທິດນີ້",
  "total_orders": "ອໍເດີ້ທັງໝົດ",
  "cash_in_your_hand": "ເງິນສົດຢູ່ກັບທ່ານ",
  "cash_on_delivery": "ເກັບເງິນປາຍທາງ",
  "digital_payment": "ຈ່າຍອອນລາຍ",
  "paid": "ຊຳລະແລ້ວ",
  "unpaid": "ຄ້າງຈ່າຍ",
  "pending": "ລໍຖ້າ",
  "accepted": "ຮັບແລ້ວ",
  "processing": "ດຳເນີນການ",
  "confirmed": "ຢືນຢັນແລ້ວ",
  "handover": "ພ້ອມສົ່ງ",
  "picked_up": "ຮັບເອົາແລ້ວ",
  "delivered": "ຈັດສົ່ງແລ້ວ",
  "refund_requested": "ຂໍເງິນຄືນ",
  "refunded": "ຄືນເງິນແລ້ວ",
  "returned": "ສົ່ງຄືນແລ້ວ",
  "failed": "ລົ້ມເຫຼວ",
  "canceled": "ຍົກເລີກແລ້ວ",
  "delivered_at": "ຈັດສົ່ງທີ່",
  "payment_info": "ລາຍລະອຽດການຈ່າຍ",
  "status": "ສະຖານະ",
  "method": "ວິທີການ",
  "prepaid_delivery": "ສົ່ງແບບຈ່າຍເງິນກ່ອນ",
  "ratings": "ໃຫ້ຄະແນນ",
  "my_ratings": "ຄະແນນຂອງຂ້ອຍ",
  "reviews": "ຣີວິວ",
  "new_order_request_from_a_customer": "ອໍເດີ້ໃໝ່ຈາກລູກຄ້າ",
  "order_request": "ຂໍອໍເດີ້",
  "cash": "ສົດ",
  "to": "ຫາ",
  "my_location": "ທີ່ຢູ່ຂ້ອຍ",
  "min": "ນາທີ",
  "earned_amount": "ເງິນທີ່ໄດ້",
  "cancel": "ຍົກເລີກ",
  "accept": "ຍອມຮັບ",
  "call_customer_for_confirmation": "ໂທຫາລູກຄ້າເພື່ອຢືນຢັນ",
  "call": "ໂທ",
  "are_you_sure_to_accept": "ທ່ານຕ້ອງການທີ່ຈະຮັບບໍ່?",
  "are_you_sure_to_cancel": "ທ່ານຕ້ອງການທີ່ຈະຍົກເລີກບໍ່?",
  "are_you_sure_to_ignore": "ທ່ານຕ້ອງການທີ່ຈະບໍ່ຮັບບໍ່?",
  "are_you_sure_to_confirm": "ທ່ານຕ້ອງການຢືນຢັນບໍ່?",
  "you_want_to_cancel_this_order": "ທ່ານຕ້ອງການຍົກເລີກອໍເດີ້ນີ້ບໍ່?",
  "you_want_to_accept_this_order": "ທ່ານຕ້ອງການຮັບອໍເດີ້ນີ້ບໍ່?",
  "you_want_to_ignore_this_order": "ທ່ານຕ້ອງການບໍ່ຮັບອໍເດີ້ນີ້ບໍ່?",
  "you_want_to_confirm_this_order": "ທ່ານຕ້ອງການຢືນຢັນອເດີ້ນີ້ບໍ່?",
  "current_order": "ອໍເດີ້ປັດຈຸບັນ",
  "completed_order": "ອໍເດີ້ສຳເລັດ",
  "item": "ລາຍການ",
  "items": "ລາຍການ",
  "restaurant_details": "ລາຍລະອຽດຮ້ານຄ້າ",
  "direction": "ເສັ້ນທາງ",
  "customer_contact_details": "ລາຍລະອຽດຕິດຕໍ່ລູກຄ້າ",
  "price": "ລາຄາ",
  "description": "ລາຍລະອຽດ",
  "mark_as_order_delivered": "ໝາຍວ່າໄດ້ສົ່ງອໍເດີ້ແລ້ວ",
  "order_successfully_delivered": "ຈັດສົ່ງອໍເດີ້ສຳເລັດແລ້ວ",
  "you_have_earned": "ທ່ານໄດ້ຮັບເງິນ",
  "back_to_home": "ກັບນ້າຫຼັກ",
  "no_order_request_available": "ບໍ່ມີຄຳຮ້ອງອໍເດີ້ເຂົ້າມາ",
  "km": "ກມ",
  "prepaid": "ຈ່າຍກ່ອນ",
  "no": "ບໍ່",
  "yes": "ແມ່ນ",
  "no_order_found": "ບໍ່ພົບອໍເດີ້",
  "my_orders": "ອໍເດີ້ຂອງຂ້ອຍ",
  "order_amount": "ມູນຄ່າອໍເດີ້",
  "invalid_phone_number_found": "ບໍພົບເບີໂທທີ່ຖືກຕ້ອງ",
  "could_not_launch": "ເປີດບໍ່ໄດ້",
  "swipe_to_pick_up_order": "ເລື່ອນເພື່ອຮັບເອົາອໍເດີ້",
  "swipe_to_deliver_order": "ເລື່ອນເພື່ອຈັດສົ່ງອໍເດີ້",
  "you_can_not_go_offline_now": "ທ່ານບໍ່ສາມາດຕັ້ງອັອຟລາຍໄດ້ຕອນນີ້ ເພາະທ່ານຍັງມີອໍເດີ້ຄ້າງຢູ່.",
  "make_yourself_online_first": "ຕ້ອງຕັ້ງເປັນອອນລາຍກ່ອນ",
  "order_details": "ລາຍລະອຽດອໍເດີ້",
  "total_amount": "ມູນຄ່າທັງໝົດ",
  "collect_otp_from_customer": "ຂໍເລກ otp ຈກາລູກຄ້າ ແລະ ຢືນຢັນການຈັດສົ່ງ",
  "ignore": "ບໍ່ຮັບ",
  "order_ignored": "ອໍເດີ້ບໍ່ໄດ້ຮັບ",
  "confirm": "ຢືນຢັນ",
  "collect_money_from_customer": "ຕ້ອງເກັບເງິນຈາກລູກຄ້າ",
  "ok": "ຕົກລົງ",
  "since_joining": "ເຂົ້າຮ່ວມແຕ່",
  "days": "ມື້ນີ້",
  "total_order": "ອໍເດີ້ທັງໝົດ",
  "dark_mode": "ໂໝດມືດ",
  "notification": "ການແຈ້ງເຕືອນ",
  "change_password": "ປ່ຽນລະຫັດ",
  "edit_profile": "ແກ້ໄຂຂໍ້ມູນສ່ວນໂຕ",
  "profile": "ຂໍ້ມູນສ່ວນໂຕ",
  "first_name": "ຊື່ແທ້",
  "last_name": "ນາມສະກຸນ",
  "enter_your_first_name": "ລະບຸຊື່ແທ້",
  "enter_your_last_name": "ລະບຸນາມສະກຸນ",
  "update": "ອັພເດດ",
  "no_notification_found": "ບໍ່ພົບການແຈ້ງເຕືອນ",
  "you_are_offline_now": "ທ່ານກຳລັງອອຟລາຍ. ທ່ານຕ້ອງອອນລາຍເພື່ອເບິ່ງເຫັນອໍເດີ້ທີ່ເຂົ້າມາ.",
  "you_have_running_order": "ທ່ານມີອໍເດີ້ຄ້າງຢູ່. ທ່ານຕ້ອງຈັດສົ່ງໃຫ້ສຳເລັດເພື່ອເບິ່ງຄຳຂໍອໍເດີ້ໃໝ່.",
  "change_something_to_update": "ປ່ຽນບາງຢ່າງເພື່ອອັພເດດ",
  "logout": "ອອກລະບົບ",
  "are_you_sure_to_logout": "ທ່ານຕ້ອງການອອກລະບົບແທ້ບໍ?",
  "are_you_sure_to_offline": "ທ່ານຕ້ອງການອອຟລາຍແທ້ບໍ່?",
  "you_denied": "ທ່ານໄດ້ປະຕິເສດໃຫ້ເຂົ້າເຖິງພິກັດຂອງທ່ານ ຫຼື ອະນຸຍາດໃຫ້ສະເພາະການນຳໃຊ້ນ້າແອັພເທົ່ານັ້ນ. ທ່ານຕ້ອງໄດ້ອະນຸຍາດໃຫ້ນຳໃຊ້ແບບຕະຫຼອດເວລາ ເພື່ອນຳໃຊ້ບໍລິການນີ້ໄດ້.",
  "you_denied_forever": "ທ່ານໄດ້ປະຕິເສດໃຫ້ເຂົ້າເຖິງພິກັດແບບຖາວອນ. ທ່ານຕ້ອງໄດ້ອະນຸຍາດໃຫ້ນຳໃຊ້ ເພື່ອນຳໃຊ້ບໍລິການນີ້ໄດ້.",
  "cod": "COD",
  "digitally_paid": "ຈ່າຍອອນລາຍ",
  "go": "ໄປ",
  "restaurant_location": "ທີ່ຕັ້ງຮ້ານອາຫານ",
  "customer_location": "ທີ່ຢູ່ລູກຄ້າ",
  "mins_ago": "ນາທີກ່ອນ",
  "order_history": "ປະຫວັດອໍເດີ້",
  "food_is_preparing": "ອາຫານກຳລັງກຽມ",
  "food_is_ready_for_handover": "ອາຫານພ້ອມຈັດສົ່ງແລ້ວ",
  "swipe_to_confirm_order": "ເລື່ອນເພື່ອຢືນຢັນອໍເດີ້",
  "food_waiting_for_cook": "ອາຫານລໍຖ້າການກະກຽມ",
  "addons": "ສ່ວນເສີມ",
  "variations": "ຕົວເລືອກ",
  "quantity": "ຈຳນວນ",
  "non_changeable": "ປ່ຽນບໍ່ໄດ້",
  "you_have_assigned_a_new_order": "ທ່ານໄດ້ຮັບມອບໝາຍອໍເດີ້ໃໝ່",
  "earnings": "ລາຍຮັບ",
  "balance": "ຍອດຄົງເຫຼືອ",
  "today": "ມື້ນີ້",
  "this_week": "ອາທິດນີ້",
  "this_month": "ເດືອນນີ້",
  "next": "ຕໍ່ໄປ",
  "for_demo_purpose": "ໃນການທົດລອງນຳໃຊ້ 1234 ເປັນ OTP",
  "this_app_collects_location_data": "ແອັບນີ້ເກັບກຳຂໍ້ມູນສະຖານທີ່ເພື່ອເປີດໃຊ້ການດຶງຂໍ້ມູນສະຖານທີ່ໃນເວລາທີ່ສະຖານະອອນລາຍຂອງທ່ານ, ເຖິງແມ່ນວ່າແອັບຈະປິດ ຫຼືບໍ່ໄດ້ໃຊ້ກໍຕາມ.",
  "running_orders": "ອໍເດີ້ຕອນນີ້",
  "terms_condition": "ຂໍ້ກຳນົດ & ເງື່ອນໄຂ",
  "privacy_policy": "ນະໂຍບາຍຄວາມເປັນສ່ວນຕົວ",
  "language": "ພາສາ",
  "select_language": "ເລືອກພາສາ",
  "select_a_language": "ເລືອກພາສາ",
  "you_can_change_language": "*ທ່ານສາມາດປ່ຽນພາສາໄດ້ໃນພາຍຫຼັງໃນເມນູການຕັ້ງຄ່າ",
  "save": "ບັນທຶກ",
  "additional_note": "ບັນທຶກເພີ່ມເຕີມ",
  "join_as_a": "ເຂົ້າຮ່ວມນຳເຮົາ",
  "delivery_man": "ຜູ້ຈັດສົ່ງ",
  "veg": "Veg",
  "non_veg": "Non Veg",
  "version": "ເວີຊັ້່ນ",
  "we_are_under_maintenance": "ພວກເຮົາຢູ່ລະຫວ່າງການປັບປຸງ",
  "your_app_is_deprecated": "ແອັພຂອງທ່ານຖືກປິດການນຳໃຊ້",
  "we_will_be_right_back": "ພວກເຮົາຈະກັບມາໄວໆນີ້",
  "wallet_payment": "ຈ່າຍຜ່ານກາເປົາ",
  "update_now": "ອັພເດດຕອນນີ້",

  "version1.4": "1.4",
  "street_number": "ເລກຖະໜົນ",
  "house": "ເຮືອນ",
  "floor": "ຊັ້ນ",
  "food_need_to_deliver_within": "ອາຫານຕ້ອງຖືກຈັດສົ່ງພາຍໃນ",

  "your_account_remove_successfully": "ການລົບບັນຊີຂອງທ່ານສຳເລັດແລ້ວ",
  "there_is_a_problem_on_removing_your_account": "ມີປັນຫາລະຫວ່າງການລົບບັນຊີຂອງທ່ານ",
  "delete_account": "ລົບບັນຊີ",
  "are_you_sure_to_delete_account": "ທ່ານຕ້ອງການລົບບັນຊີແທ້ບໍ່?",
  "it_will_remove_your_all_information": "ຂໍ້ມູນຂອງທ່ານທັງໝົດຈະຖືກລົບ.",
  "no_restaurant_data_found": "ບໍ່ພົບຂໍ້ມູນຮ້ານອາຫານ",
  "write_some_thing": "ຂຽນບາງຢ່າງ",
  "type_here": "ພິມບ່ອນນີ້",
  "message": "ຂໍ້ຄວາມ",
  "chat_list": "ລາຍການແຊັດ",
  "conversation_list": "ລາຍການສົນທະນາ",
  "no_conversation_found": "ບໍພົບການສົນທະນາ",
  "conversation": "ການສົນທະນາ",
  "customer": "ລູກຄ້າ",
  "vendor": "ຮ້ານຄ້າ",
  "type": "ປະເພດ",
  "receiver_name": "ຊື່ຜູ້ຮັບ",
  "write_somethings": "ຂຽນບາງຢ່າງ",
  "join_as_a_delivery_man": "ເຂົ້າຮ່ວມເປັນຜູ້ຈັດສົ່ງ",
  "delivery_man_registration": "ການລົງທະບຽນຜູ້ຈັດສົ່ງ",
  "delivery_man_image": "ຮູບຜພາບຜູ້ຈັດສົ່ງ",
  "identity_type": "ປະເພດການຢືນຢັນຕົວຕົນ",
  "passport": "ພາສປອດ",
  "driving_license": "ໃບຂັບຂີ່",
  "nid": "ບັດປະຈຳຕົວ",
  "identity_number": "ເລກເອກະສານຢືນຢັນ",
  "identity_images": "ຮູບພາບເອກະສານ",
  "submit": "ສົ່ງໄປ",
  "delivery_man_registration_successful": "ການລົງທະບຽນຜູ້ຈັດສົ່ງສຳເລັດແລ້ວ",
  "enter_delivery_man_first_name": "ລະບຸຊື່ແທ້ຜູ້ຈັດສົ່ງ",
  "enter_delivery_man_last_name": "ລະບຸນາມສະກຸນຜູ້ຈັດສົ່ງ",
  "enter_delivery_man_email_address": "ລະບຸອີເມວຂອງຜູ້ຈັດສົ່ງ",
  "enter_delivery_man_phone_number": "ລະບຸເບີໂທຂອງຜູ້ຈັດສົ່ງ",
  "enter_a_valid_phone_number": "ໃສ່ເບີໂທທີ່ຖືກຕ້ອງ",
  "enter_password_for_delivery_man": "ໃສ່ລະຫັດຜ່ານສຳລັບຜູ້ຈັດສົ່ງ",
  "enter_delivery_man_identity_number": "ລະບຸເລກທີເອກະສານຢືນຢັນຕົວຕົນ",
  "upload_delivery_man_image": "ອັພໂຫຼດຮູບພາບເອກະສານ",
  "delivery_man_type": "ປະເພດຜູ້ຈັດສົ່ງ",
  "zone": "ເຂດ",
  "freelancer": "ອິດສະລະ",
  "salary_based": "ປະຈຳບໍລິສັດ",
  "user": "ລູກຄ້າ",
  "search": "ຄົ້ນຫາ",
  "not_found": "ບໍ່ພົບ",
  "deleted": "ລົບແລ້ວ",
  "customer_not_found": "ບໍ່ພົບລູກຄ້າ",
  "no_message_found": "ບໍ່ພົບຂໍ້ຄວາມ",
  "restaurant_have_no_chat_permission": "ຮ້ານຄ້າບໍ່ໄດ້ຮັບອະນຸຍາດໃນການແຊັດ",
  "select_cancellation_reasons": "ເລືອກເຫດຜົນການຍົກເລີກ",
  "no_reasons_available": "ບໍ່ມີເຫດຜົນ",
  "you_did_not_select_select_any_reason": "ທ່ານບໍ່ໄດ້ເລືອກເຫດຜົນ",
  "with": "ກັບ",
  "please_select_vehicle_for_the_deliveryman": "ກະລຸນາເລືອກປະເພດພາຫະນະ",
  "vehicle_type": "ປະເພດພາຫະນະ",
  "select_shift": "ເລືອກກະວຽກ",
  "you_did_not_select_any_shift": "ທ່ານບໍ່ໄດ້ເລືອກກະວຽກ",
  "skip": "ຜ່ານ",
  "incentive_offers": "ຂໍ້ສະເໜີອຸດໜູນ",
  "incentive": "ເງິນອຸດໜູນ",
  "current_incentive_offers": "ຂໍ້ສະເໜີອຸດໜູນປັດຈຸບັນ",
  "earn_per_day": "ລາຍຮັບຕໍ່ມື້",
  "you_will_get": "ທ່ານຈະໄດ້",
  "you_have_total_incentive": "ທ່ານມີເງິນອຸດໜູນທັງໝົດ",
  "no_offer_available": "ບໍ່ມີຂໍ້ສະເໜີ",
  "shift": "ກະວຽກ",
  "earning": "ລາຍຮັບ",
  "cutlery": "ບ່ວງສ້ອມ",
  "delivery_instruction": "ຄຳແນະນຳໃນການສົ່ງ",
  "unavailable_item_note": "ບັນທຶກສິນຄ້າທີ່ບໍ່ມີ",
  "complete_registration_process_to_serve_as_delivery_man_in_this_platform": "ສືບຕໍ່ລົງທະບຽນໃຫ້ສຳເລັດເພື່ອເລີ່ມຕົ້ນເປັນຜູ້ຮັບສົ່ງໃນລະບົບຂອງພວກເຮົາ",
  "upload_deliveryman_photo": "ອັພໂຫຼດຮູບ \nຂອງຜູ້ຈັດສົ່ງ",
  "upload_identity_image": "ອັພໂຫ5ດຮູບເອກະສານ",
  "select_delivery_type": "ເລືອກປະເພດຜູ້ຮັບສົ່ງ",
  "select_vehicle": "ເລືອກພາຫະນະ",

  "8_or_more_character": "8 ຕົວອັກສອນຫຼືຫຼາຍກວ່ານັ້ນ",
  "1_number": "1 ຕົວເລກ",
  "1_upper_case": "1 ຕົວອັກສອນໃຫຍ່",
  "1_lower_case": "1 ຕົວອັກສອນນ້ອຍ",
  "1_special_character": "1 ຕົວອັກສອນພິເສດ",
  "password_does_not_match": "ລະຫັດຜ່ານບໍ່ກົງກັນ",
  "please_select_delivery_type": "ກະລຸນາເລືອກປະເພດຜູ້ຈັດສົ່ງ",
  "please_add_your_identity_image": "ກະລຸານເພີມຮູບພາບເອກະສານຂອງທ່ານ",
  "take_a_picture": "ຖ່າຍຮູບ",
  "from_camera": "ຈາກກ້ອງຖ່າຍ",
  "from_gallery": "ຈາກຄັງພາບ",
  "enter_otp_number": "ໃສ່ເລກ OTP",
  "did_not_receive_user_notification": "ບໍ່ໄດ້ຮັບການແຈ້ງເຕືອນຂອງຜູ້ໃຊ້ງານ?",
  "resend_it": "ສົ່ງໃໝ່",
  "order_proof": "ຫຼັກຖານອໍເດີ້",
  "item_price": "ລາຄາສິນຄ້າ",
  "subtotal": "ຍອດລວມ",
  "tax_included": "ລວມອາກອນ",
  "discount": "ສ່ວນຫຼຸດ",
  "delivery_man_tips": "ທິບຜູ້ຈັດສົ່ງ",
  "coupon_discount": "ສ່ວນຫຼຸດຄູປອງ",
  "vat_tax": "Vat/Tax",
  "delivery_fee": "ຄ່າຈັດສົ່ງ",
  "paid_by_wallet": "ຈ່າຍຜ່ານກະເປົາ",
  "due_amount": "ຍອດຄ້າງຈ່າຍ",
  "completed_after_delivery_picture": "ຮູບຢັ້ງຢືນການຈັດສົ່ງສຳເລັດ",
  "Remove it form my cart": "ລົບອອກຈາກກະຕ່າ",
  "Remove it from my cart": "ລົບອອກຈາກກະຕ່າຂອງຂ້ອຍ",
  "Deliver to the reception desk": "ສົ່ງຮອດບ່ອນຕ້ອນຮັບ",
  "complete_delivery": "ການຈັດສົ່ງສຳເລັດ",
  "paid_by": "ຈ່າຍໂດຍ",

  "cash_in_hand": "ເງິນສົດນຳທ່ານ",
  "transaction_history": "ປະຫວັດທຸລະກຳ",
  "paid_via": "ຈ່າຍຜ່ານ",
  "attention_please" : "ໂປດຊາບ !",
  "pay_the_due" : "ຊຳລະຍອດຄ້າງຈ່າຍ",
  "pay_now" : "ຈ່າຍຕອນນີ້",
  "disbursement" : "ການເບີກຈ່າຍ",
  "disbursement_history" : "ປະຫວັດການເບີກຈ່າຍ",
  "payment_information" : "ຂໍ້ມູນການເບີກຈ່າຍ",
  "you_payment_has_been_completed_your_will_receive_the_amount_within_7_day_please_wait_till_then" : "ການຊຳລະຂອງທ່ານສຳເລັດ. ທ່ານຈະໄດ້ຮັບຍອດເງິນພາຍໃນ 7 ມືທຳການ. ກະລຸນາລໍຖ້າ.",
  "disbursement_id" : "ເລກທີການເບີກຈ່າຍ",
  "withdraw_methods" : "ວິທີການຖອນ",
  "withdraw_methods_attention_message" : "ກະລຸນາອັພເດດຢ່າງໜ້ອຍໜື່ງວິທີການຖອນ ແລະຕັ້ງເປັນວິທີການຫຼັກຂອງທ່ານ. ຖ້າບໍ່ດັ່ງນັ້ນແອັດມິນຈະບໍ່ສາມາດເບີກຖອນຈຳນວນເງິນໃຫ້ທ່ານໄດ້.",
  "make_default" : "ຕັ້ງເປັນຫຼັກ",
  "edit_details" : "ແກ້ໄຂຂໍ້ມູນ",
  "add_withdraw_method" : "ເພີ່ມວິທີການຖອນ",
  "add_method" : "ເພີ່ມວິທີການ",
  "account_holder" : "ເຈົາຂອງບັນຊີ",
  "account_number" : "ເລກທີບັນຊີ",
  "update_information" : "ອັພເດດຂໍ້ມູນ",
  "edit_withdraw_method" : "ແກ້ໄຂວິທີການຖອນ",
  "payment_method": "ວິທີການການຈ່າຍ",
  "bank_name": "ຊື່ທະນາຄານ",
  "branch_name": "ຊື່ສາຂາ",
  "pay_via_online" : "ຈ່າຍອອນລາຍ",
  "faster_and_secure_way_to_pay_bill" : "ຊ່ອງທາງການຊຳລະທີ່ໄວ ແລະ ປອດໄພກວ່າ",
  "select" : "ເລືອກ",
  "wallet_adjustment_successfully" : "ການປັບກະເປົາເງິນສຳເລັດ",
  "do_you_want_to_cancel_this_payment" : "ທ່ານຕ້ອງການຍົກເລີກການຈ່າຍນີ້ແມ່ນບໍ່?",
  "cancel_payment" : "ຍົກເລີກການຈ່າຍ",
  "payment" : "ການຈ່າຍ",
  "your_payment_is_successfully_completed" : "ການຈ່າຍຂອງທ່ານສຳເລັດແລ້ວ",
  "your_payment_is_not_done" : "ການຈ່າຍເງິນຂອງທ່ານຍັງບໍ່ແລ້ວເທື່ອ",
  "okay" : "ຕົກລົງ",
  "over_flow_block_warning_message" : "ຍອດເງິນສົດນຳທ່ານໄດ້ເກີນທີ່ໄດ້ກຳນົດໄວ້ແລ້ວ. ບັນຊີຂອງທ່ານຈະຖືກລະງັບໄວ້ຈົນກວ່າທ່ານຈະໄດ້ຈ່າຍເງິນຕາມກຳນົດ. ທ່ານຈະບໍ່ໄດ້ຮັບຄຳຮ້ອງອໍເດີ້ອີກຕັ້ງແຕ່ນີ້ໄປ.",
  "over_flow_warning_message" : "ຍອດກຳນົດຖືເງິນສົດຂອງທ່ານກຳລັງຈະເຕັມວົງເງິນແລ້ວ. ກະລຸນາຈ່າຍເງິນຕາມຈຳນວນທີ່ຄົບກຳນົດ ບໍ່ດັ່ງນັ້ນບັນຊີຂອງທ່ານຈະຖືກລະງັບຖ້າຍອດຮອດຈຳນວນທີ່ກຳນົດ",
  "no_transaction_found" : "ບໍ່ພົບທຸລະກຳ",
  "payable_amount" : "ຈຳນວນທີ່ຕ້ອງຈ່າຍ",
  "cash_adjustment" : "ການປັບເງິນສົດ",
  "cash_adjustment_description" : "ຫາກຕ້ອງການປັບຍອດເງິນສົດຄົງເຫຼືອ ແລະ ຈຳນວນທີ່ຖອນໄດ້ກະລຸນາກົດ 'ຕົກລົງ' ເພື່ອຢືນຢັນການປັບປ່ຽນ",
  "adjust_payments" : "ປັບການຈ່າຍເງິນ",
  "withdrawal_amount" : "ຈຳນວນເງິນທີ່ຖອນ",
  "add_successfully" : "ເພີ່ມສຳເລັດ",
  "set_default_method_successful" : "ຕັ້ງວິທີການຫຼັກສຳເລັດ",
  "method_delete_successfully" : "ລົບວິທີການສຳເລັດ",
  "pending_disbursements" : "ຢູ່ລະຫວ່າງການເບີກຈ່າຍ",
  "completed_disbursements" : "ເບີກຈ່າຍຮຽບຮ້ອຍແລ້ວ",
  "canceled_transactions" : "ທຸລະກຳທີ່ຖືກຍົກເລີກ",
  "completed" : "ສຳເລັດ",
  "no_history_available" : "ບໍ່ມີປະຫວັດ",
  "are_you_sure_to_delete_this_method" : "ທ່ານແນ່ໃຈບໍ່ວ່າຈະລົບວິທີການນີ້?",
  "no_method_found" : "ບໍ່ພົບວິທີການ",
  "select_payment_method" : "ເລືອກວິທີການຈ່າຍ",
  "required_fields_can_not_be_empty" : "ຊ່ອງທີ່ຈຳເປັນຕອ້ງບໍ່ເວັ້ນວ່າງ",
  "default_method" : "ວິທີການຫຼັກ",
  "delete" : "ລົບ",
  "set_default_withdraw_method" : "ຕັ້ງວິທີການຖອນເງິນຫຼັກ",
  "limit_exceeded" : "ເກີນທີ່ກຳນົດແລ້ວ",
  "please_upload_lower_size_file": "ກະລຸນາອັພໂຫູດໄຟລ໌ຂະໜາດນ້ອຍກວ່ານີ້",
  "can_not_be_empty": "ບໍ່ສາມາດເວັ້ນວ່າງໄດ້",
  "please_add": "ກະລຸນາເພີ່ມ",
  "not_set_yet": "ຍັງບໍ່ໄດ້ຕັ້ງ",
  "please_set_data_in": "ກະລຸນາຕັ້ງຄ່າຂໍ້ມູນໃນ",
  "view_details": "ເບິ່ງລາຍລະອຽດ",
  "my_account": "ບັນຊີຂອງຂ້ອຍ",
  "deliver_to": "ຈັດສົ່ງໄປ",
  "view_on_map": "ເບິ່ງເທິງແຜນທີ່",
  "restaurant_is": "ຮ້ານອາຫານແມ່ນ",
  "km_away_from_you": "ກມ ໄກຈາກທ່ານ",
  "order_location": "ສະຖານທີ່ອໍເດີ້",
  "your_distance_from_restaurant": "ໄລຍະທາງຂອງທ່ານຈາກຮ້ານອາຫານ",
  "from_customer_to_restaurant_distance": "ໄລຍະທາງຈາກລູກຄ້າຫາຮ້ານອາຫານ",
  "km_aprox": "ກມ ໂດຍປະມານ",
  "disbursement_methods": "ຊ່ອງທາງການເບີກຈ່າຍ",
  "currently_there_are_no_payment_options_available_please_contact_admin_regarding_any_payment_process_or_queries" : "ໃນປັດຈຸບັນ, ບໍ່ມີທາງເລືອກໃນການຊໍາລະເງິນ. ກະລຸນາຕິດຕໍ່ຜູ້ເບິ່ງແຍງກ່ຽວກັບຂະບວນການຊໍາລະເງິນ ຫຼືການສອບຖາມ.",
  "you_do_not_have_sufficient_balance_to_pay_the_minimum_payable_balance_is" : "ທ່ານບໍ່ມີຍອດເງິນພຽງພໍໃນການຈ່າຍເງິນ. ຍອດເງິນທີ່ຕ້ອງຈ່າຍຕໍ່າສຸດແມ່ນ",
  "total_withdrawn" : "ຖອນທັງໝົດ",
  "payment_method_deleted" : "ລຶບວິທີການຊໍາລະແລ້ວ",
  "extra_packaging" : "ການຫຸ້ມຫໍ່ພິເສດ",
  "referral_discount" : "ສ່ວນຫຼຸດການຊັກຊວນ"
}